{
  "id": "session_1757600781798_fxpbwz3c2",
  "timestamp": "2025-09-11T14:26:21.798Z",
  "imageHash": "016a81319ca9d3b447ffceef2a487c7d",
  "walls": [
    {
      "id": "wall_bold_h_18",
      "type": "interior",
      "source": "ai-detection",
      "coordinates": {
        "x1": 434,
        "y1": 293,
        "x2": 504,
        "y2": 293
      },
      "thickness": 2,
      "confidence": 0.9,
      "isManual": false,
      "isDeleted": false
    },
    {
      "id": "wall_bold_h_19",
      "type": "interior",
      "source": "ai-detection",
      "coordinates": {
        "x1": 627,
        "y1": 293,
        "x2": 726,
        "y2": 293
      },
      "thickness": 0,
      "confidence": 0.9,
      "isManual": false,
      "isDeleted": false
    },
    {
      "id": "wall_bold_h_24",
      "type": "interior",
      "source": "ai-detection",
      "coordinates": {
        "x1": 434,
        "y1": 317,
        "x2": 504,
        "y2": 317
      },
      "thickness": 2,
      "confidence": 0.9,
      "isManual": false,
      "isDeleted": false
    },
    {
      "id": "wall_bold_h_25",
      "type": "interior",
      "source": "ai-detection",
      "coordinates": {
        "x1": 627,
        "y1": 317,
        "x2": 726,
        "y2": 317
      },
      "thickness": 0,
      "confidence": 0.9,
      "isManual": false,
      "isDeleted": false
    },
    {
      "id": "wall_bold_h_30",
      "type": "interior",
      "source": "ai-detection",
      "coordinates": {
        "x1": 63,
        "y1": 613,
        "x2": 143,
        "y2": 613
      },
      "thickness": 0,
      "confidence": 0.9,
      "isManual": false,
      "isDeleted": false
    },
    {
      "id": "wall_bold_h_35",
      "type": "interior",
      "source": "ai-detection",
      "coordinates": {
        "x1": 63,
        "y1": 637,
        "x2": 143,
        "y2": 637
      },
      "thickness": 0,
      "confidence": 0.9,
      "isManual": false,
      "isDeleted": false
    },
    {
      "id": "wall_bold_h_36",
      "type": "interior",
      "source": "ai-detection",
      "coordinates": {
        "x1": 312,
        "y1": 637,
        "x2": 377,
        "y2": 637
      },
      "thickness": 5,
      "confidence": 0.9,
      "isManual": false,
      "isDeleted": false
    },
    {
      "id": "wall_bold_h_37",
      "type": "interior",
      "source": "ai-detection",
      "coordinates": {
        "x1": 541,
        "y1": 637,
        "x2": 726,
        "y2": 637
      },
      "thickness": 0,
      "confidence": 0.9,
      "isManual": false,
      "isDeleted": false
    },
    {
      "id": "wall_bold_h_42",
      "type": "interior",
      "source": "ai-detection",
      "coordinates": {
        "x1": 63,
        "y1": 661,
        "x2": 143,
        "y2": 661
      },
      "thickness": 0,
      "confidence": 0.9,
      "isManual": false,
      "isDeleted": false
    },
    {
      "id": "wall_bold_h_43",
      "type": "interior",
      "source": "ai-detection",
      "coordinates": {
        "x1": 312,
        "y1": 661,
        "x2": 377,
        "y2": 661
      },
      "thickness": 0,
      "confidence": 0.9,
      "isManual": false,
      "isDeleted": false
    },
    {
      "id": "wall_bold_v_72",
      "type": "interior",
      "source": "ai-detection",
      "coordinates": {
        "x1": 229,
        "y1": 623,
        "x2": 229,
        "y2": 733
      },
      "thickness": 1,
      "confidence": 0.9,
      "isManual": false,
      "isDeleted": false
    },
    {
      "id": "wall_bold_v_88",
      "type": "interior",
      "source": "ai-detection",
      "coordinates": {
        "x1": 429,
        "y1": 39,
        "x2": 429,
        "y2": 179
      },
      "thickness": 1,
      "confidence": 0.9,
      "isManual": false,
      "isDeleted": false
    },
    {
      "id": "wall_bold_v_89",
      "type": "interior",
      "source": "ai-detection",
      "coordinates": {
        "x1": 429,
        "y1": 280,
        "x2": 429,
        "y2": 461
      },
      "thickness": 0,
      "confidence": 0.9,
      "isManual": false,
      "isDeleted": false
    },
    {
      "id": "wall_bold_v_97",
      "type": "interior",
      "source": "ai-detection",
      "coordinates": {
        "x1": 453,
        "y1": 39,
        "x2": 453,
        "y2": 179
      },
      "thickness": 2,
      "confidence": 0.9,
      "isManual": false,
      "isDeleted": false
    },
    {
      "id": "wall_bold_v_100",
      "type": "interior",
      "source": "ai-detection",
      "coordinates": {
        "x1": 477,
        "y1": 39,
        "x2": 477,
        "y2": 179
      },
      "thickness": 2,
      "confidence": 0.9,
      "isManual": false,
      "isDeleted": false
    },
    {
      "id": "wall_bold_v_101",
      "type": "interior",
      "source": "ai-detection",
      "coordinates": {
        "x1": 541,
        "y1": 623,
        "x2": 541,
        "y2": 730
      },
      "thickness": 2,
      "confidence": 0.9,
      "isManual": false,
      "isDeleted": false
    },
    {
      "id": "wall_bold_v_104",
      "type": "interior",
      "source": "ai-detection",
      "coordinates": {
        "x1": 693,
        "y1": 623,
        "x2": 693,
        "y2": 841
      },
      "thickness": 0,
      "confidence": 0.9,
      "isManual": false,
      "isDeleted": false
    }
  ],
  "rooms": [
    {
      "id": "room_1",
      "name": "Room 1",
      "type": "unknown",
      "squareFootage": 132931.5,
      "isExterior": false,
      "vertices": [
        {
          "x": 63,
          "y": 39
        },
        {
          "x": 394.5,
          "y": 39
        },
        {
          "x": 394.5,
          "y": 440
        },
        {
          "x": 63,
          "y": 440
        }
      ],
      "source": "ai-detection",
      "isManual": false,
      "isDeleted": false
    },
    {
      "id": "room_2",
      "name": "Room 2",
      "type": "unknown",
      "squareFootage": 132931.5,
      "isExterior": false,
      "vertices": [
        {
          "x": 394.5,
          "y": 39
        },
        {
          "x": 726,
          "y": 39
        },
        {
          "x": 726,
          "y": 440
        },
        {
          "x": 394.5,
          "y": 440
        }
      ],
      "source": "ai-detection",
      "isManual": false,
      "isDeleted": false
    },
    {
      "id": "room_3",
      "name": "Room 3",
      "type": "unknown",
      "squareFootage": 132931.5,
      "isExterior": false,
      "vertices": [
        {
          "x": 63,
          "y": 440
        },
        {
          "x": 394.5,
          "y": 440
        },
        {
          "x": 394.5,
          "y": 841
        },
        {
          "x": 63,
          "y": 841
        }
      ],
      "source": "ai-detection",
      "isManual": false,
      "isDeleted": false
    },
    {
      "id": "room_4",
      "name": "Room 4",
      "type": "unknown",
      "squareFootage": 132931.5,
      "isExterior": false,
      "vertices": [
        {
          "x": 394.5,
          "y": 440
        },
        {
          "x": 726,
          "y": 440
        },
        {
          "x": 726,
          "y": 841
        },
        {
          "x": 394.5,
          "y": 841
        }
      ],
      "source": "ai-detection",
      "isManual": false,
      "isDeleted": false
    }
  ],
  "doors": [],
  "windows": [],
  "measurements": [],
  "metadata": {
    "totalWalls": 17,
    "totalRooms": 4,
    "totalDoors": 0,
    "totalWindows": 0,
    "totalMeasurements": 0,
    "manualEdits": 0,
    "deletions": 0,
    "detectionMethods": [],
    "aiWalls": null,
    "processingTime": 506540085
  }
}