{
  "id": "session_1757438890181_xiyiinygc",
  "timestamp": "2025-09-09T17:28:10.181Z",
  "imageHash": "8ac4c540be30ce2e30f05c0900fd4377",
  "walls": [
    {
      "id": "wall_h_1",
      "type": "interior",
      "source": "ai-detection",
      "coordinates": {
        "x1": 99.8125,
        "y1": 302,
        "x2": 99.8125,
        "y2": 457
      },
      "thickness": 5,
      "confidence": 0.8,
      "isManual": false,
      "isDeleted": false
    },
    {
      "id": "wall_h_2",
      "type": "interior",
      "source": "ai-detection",
      "coordinates": {
        "x1": 123,
        "y1": 346,
        "x2": 165,
        "y2": 346
      },
      "thickness": 5,
      "confidence": 0.95,
      "isManual": false,
      "isDeleted": false
    },
    {
      "id": "wall_h_4",
      "type": "interior",
      "source": "ai-detection",
      "coordinates": {
        "x1": 502,
        "y1": 386,
        "x2": 557,
        "y2": 386
      },
      "thickness": 5,
      "confidence": 0.6,
      "isManual": false,
      "isDeleted": false
    },
    {
      "id": "wall_h_7",
      "type": "interior",
      "source": "ai-detection",
      "coordinates": {
        "x1": 702,
        "y1": 386,
        "x2": 794,
        "y2": 386
      },
      "thickness": 5,
      "confidence": 0.8,
      "isManual": false,
      "isDeleted": false
    },
    {
      "id": "wall_h_3",
      "type": "interior",
      "source": "ai-detection",
      "coordinates": {
        "x1": 339.25,
        "y1": 418,
        "x2": 339.25,
        "y2": 471
      },
      "thickness": 5,
      "confidence": 0.8,
      "isManual": false,
      "isDeleted": false
    },
    {
      "id": "wall_h_5",
      "type": "interior",
      "source": "ai-detection",
      "coordinates": {
        "x1": 501,
        "y1": 426,
        "x2": 549,
        "y2": 426
      },
      "thickness": 5,
      "confidence": 0.6,
      "isManual": false,
      "isDeleted": false
    },
    {
      "id": "wall_h_8",
      "type": "interior",
      "source": "ai-detection",
      "coordinates": {
        "x1": 702,
        "y1": 426,
        "x2": 794,
        "y2": 426
      },
      "thickness": 5,
      "confidence": 0.8,
      "isManual": false,
      "isDeleted": false
    },
    {
      "id": "wall_h_0",
      "type": "interior",
      "source": "ai-detection",
      "coordinates": {
        "x1": 140.125,
        "y1": 425,
        "x2": 140.125,
        "y2": 473
      },
      "thickness": 5,
      "confidence": 0.6,
      "isManual": false,
      "isDeleted": false
    },
    {
      "id": "wall_h_3",
      "type": "interior",
      "source": "ai-detection",
      "coordinates": {
        "x1": 459.125,
        "y1": 512,
        "x2": 459.125,
        "y2": 627
      },
      "thickness": 5,
      "confidence": 0.6,
      "isManual": false,
      "isDeleted": false
    },
    {
      "id": "wall_h_0",
      "type": "interior",
      "source": "ai-detection",
      "coordinates": {
        "x1": 104,
        "y1": 586,
        "x2": 104,
        "y2": 631
      },
      "thickness": 5,
      "confidence": 0.6,
      "isManual": false,
      "isDeleted": false
    },
    {
      "id": "wall_h_1",
      "type": "interior",
      "source": "ai-detection",
      "coordinates": {
        "x1": 181.75,
        "y1": 586,
        "x2": 181.75,
        "y2": 630
      },
      "thickness": 5,
      "confidence": 0.95,
      "isManual": false,
      "isDeleted": false
    },
    {
      "id": "wall_h_4",
      "type": "interior",
      "source": "ai-detection",
      "coordinates": {
        "x1": 822.125,
        "y1": 586,
        "x2": 822.125,
        "y2": 642
      },
      "thickness": 5,
      "confidence": 0.6,
      "isManual": false,
      "isDeleted": false
    },
    {
      "id": "wall_h_0",
      "type": "interior",
      "source": "ai-detection",
      "coordinates": {
        "x1": 60,
        "y1": 626,
        "x2": 190,
        "y2": 626
      },
      "thickness": 5,
      "confidence": 0.6,
      "isManual": false,
      "isDeleted": false
    },
    {
      "id": "wall_h_2",
      "type": "interior",
      "source": "ai-detection",
      "coordinates": {
        "x1": 299,
        "y1": 626,
        "x2": 583,
        "y2": 626
      },
      "thickness": 5,
      "confidence": 0.6,
      "isManual": false,
      "isDeleted": false
    },
    {
      "id": "wall_h_3",
      "type": "interior",
      "source": "ai-detection",
      "coordinates": {
        "x1": 724,
        "y1": 626,
        "x2": 900,
        "y2": 626
      },
      "thickness": 5,
      "confidence": 0.8,
      "isManual": false,
      "isDeleted": false
    },
    {
      "id": "wall_h_0",
      "type": "interior",
      "source": "ai-detection",
      "coordinates": {
        "x1": 856.875,
        "y1": 768,
        "x2": 856.875,
        "y2": 817
      },
      "thickness": 5,
      "confidence": 0.6,
      "isManual": false,
      "isDeleted": false
    },
    {
      "id": "wall_h_0",
      "type": "interior",
      "source": "ai-detection",
      "coordinates": {
        "x1": 668.25,
        "y1": 826,
        "x2": 668.25,
        "y2": 869
      },
      "thickness": 5,
      "confidence": 0.6,
      "isManual": false,
      "isDeleted": false
    },
    {
      "id": "wall_h_0",
      "type": "interior",
      "source": "ai-detection",
      "coordinates": {
        "x1": 299,
        "y1": 839,
        "x2": 299,
        "y2": 891
      },
      "thickness": 5,
      "confidence": 0.6,
      "isManual": false,
      "isDeleted": false
    },
    {
      "id": "wall_h_1",
      "type": "interior",
      "source": "ai-detection",
      "coordinates": {
        "x1": 636,
        "y1": 866,
        "x2": 676,
        "y2": 866
      },
      "thickness": 5,
      "confidence": 0.8,
      "isManual": false,
      "isDeleted": false
    },
    {
      "id": "wall_h_2",
      "type": "interior",
      "source": "ai-detection",
      "coordinates": {
        "x1": 729,
        "y1": 866,
        "x2": 788,
        "y2": 866
      },
      "thickness": 5,
      "confidence": 0.8,
      "isManual": false,
      "isDeleted": false
    },
    {
      "id": "wall_h_3",
      "type": "interior",
      "source": "ai-detection",
      "coordinates": {
        "x1": 820.625,
        "y1": 853,
        "x2": 820.625,
        "y2": 917
      },
      "thickness": 5,
      "confidence": 0.6,
      "isManual": false,
      "isDeleted": false
    },
    {
      "id": "wall_h_1",
      "type": "interior",
      "source": "ai-detection",
      "coordinates": {
        "x1": 124,
        "y1": 1066,
        "x2": 199,
        "y2": 1066
      },
      "thickness": 5,
      "confidence": 0.6,
      "isManual": false,
      "isDeleted": false
    },
    {
      "id": "wall_h_8",
      "type": "interior",
      "source": "ai-detection",
      "coordinates": {
        "x1": 531,
        "y1": 1066,
        "x2": 646,
        "y2": 1066
      },
      "thickness": 5,
      "confidence": 0.8,
      "isManual": false,
      "isDeleted": false
    },
    {
      "id": "wall_h_0",
      "type": "interior",
      "source": "ai-detection",
      "coordinates": {
        "x1": 539.75,
        "y1": 1049,
        "x2": 539.75,
        "y2": 1281
      },
      "thickness": 5,
      "confidence": 0.95,
      "isManual": false,
      "isDeleted": false
    },
    {
      "id": "wall_h_1",
      "type": "interior",
      "source": "ai-detection",
      "coordinates": {
        "x1": 584.75,
        "y1": 1049,
        "x2": 584.75,
        "y2": 1106
      },
      "thickness": 5,
      "confidence": 0.8,
      "isManual": false,
      "isDeleted": false
    },
    {
      "id": "wall_v_4",
      "type": "interior",
      "source": "ai-detection",
      "coordinates": {
        "x1": 60,
        "y1": 594,
        "x2": 60,
        "y2": 703
      },
      "thickness": 5,
      "confidence": 0.6,
      "isManual": false,
      "isDeleted": false
    },
    {
      "id": "wall_v_1",
      "type": "interior",
      "source": "ai-detection",
      "coordinates": {
        "x1": 140,
        "y1": 302,
        "x2": 140,
        "y2": 398
      },
      "thickness": 5,
      "confidence": 0.6,
      "isManual": false,
      "isDeleted": false
    },
    {
      "id": "wall_v_0",
      "type": "exterior",
      "source": "ai-detection",
      "coordinates": {
        "x1": 460,
        "y1": 226,
        "x2": 460,
        "y2": 486
      },
      "thickness": 5,
      "confidence": 0.6,
      "isManual": false,
      "isDeleted": false
    },
    {
      "id": "wall_v_0",
      "type": "exterior",
      "source": "ai-detection",
      "coordinates": {
        "x1": 540,
        "y1": 372,
        "x2": 540,
        "y2": 437
      },
      "thickness": 5,
      "confidence": 0.6,
      "isManual": false,
      "isDeleted": false
    },
    {
      "id": "wall_v_1",
      "type": "interior",
      "source": "ai-detection",
      "coordinates": {
        "x1": 620,
        "y1": 1037,
        "x2": 620,
        "y2": 1095
      },
      "thickness": 5,
      "confidence": 0.8,
      "isManual": false,
      "isDeleted": false
    },
    {
      "id": "wall_v_3",
      "type": "interior",
      "source": "ai-detection",
      "coordinates": {
        "x1": 660,
        "y1": 1119,
        "x2": 660,
        "y2": 1173
      },
      "thickness": 5,
      "confidence": 0.6,
      "isManual": false,
      "isDeleted": false
    },
    {
      "id": "wall_v_3",
      "type": "interior",
      "source": "ai-detection",
      "coordinates": {
        "x1": 700,
        "y1": 994,
        "x2": 700,
        "y2": 1034
      },
      "thickness": 5,
      "confidence": 0.6,
      "isManual": false,
      "isDeleted": false
    },
    {
      "id": "wall_v_0",
      "type": "exterior",
      "source": "ai-detection",
      "coordinates": {
        "x1": 740,
        "y1": 229,
        "x2": 740,
        "y2": 282
      },
      "thickness": 5,
      "confidence": 0.6,
      "isManual": false,
      "isDeleted": false
    },
    {
      "id": "wall_v_1",
      "type": "interior",
      "source": "ai-detection",
      "coordinates": {
        "x1": 740,
        "y1": 312,
        "x2": 740,
        "y2": 352
      },
      "thickness": 5,
      "confidence": 0.6,
      "isManual": false,
      "isDeleted": false
    },
    {
      "id": "wall_v_3",
      "type": "interior",
      "source": "ai-detection",
      "coordinates": {
        "x1": 740,
        "y1": 383,
        "x2": 740,
        "y2": 439
      },
      "thickness": 5,
      "confidence": 0.8,
      "isManual": false,
      "isDeleted": false
    },
    {
      "id": "wall_v_0",
      "type": "exterior",
      "source": "ai-detection",
      "coordinates": {
        "x1": 780,
        "y1": 226,
        "x2": 780,
        "y2": 642
      },
      "thickness": 5,
      "confidence": 0.8,
      "isManual": false,
      "isDeleted": false
    },
    {
      "id": "wall_v_1",
      "type": "interior",
      "source": "ai-detection",
      "coordinates": {
        "x1": 780,
        "y1": 853,
        "x2": 780,
        "y2": 1173
      },
      "thickness": 5,
      "confidence": 0.8,
      "isManual": false,
      "isDeleted": false
    }
  ],
  "rooms": [
    {
      "id": "room_1",
      "name": "Room 1",
      "type": "unknown",
      "squareFootage": 221550,
      "isExterior": false,
      "vertices": [
        {
          "x": 60,
          "y": 226
        },
        {
          "x": 480,
          "y": 226
        },
        {
          "x": 480,
          "y": 753.5
        },
        {
          "x": 60,
          "y": 753.5
        }
      ],
      "source": "ai-detection",
      "isManual": false,
      "isDeleted": false
    },
    {
      "id": "room_2",
      "name": "Room 2",
      "type": "unknown",
      "squareFootage": 221550,
      "isExterior": false,
      "vertices": [
        {
          "x": 480,
          "y": 226
        },
        {
          "x": 900,
          "y": 226
        },
        {
          "x": 900,
          "y": 753.5
        },
        {
          "x": 480,
          "y": 753.5
        }
      ],
      "source": "ai-detection",
      "isManual": false,
      "isDeleted": false
    },
    {
      "id": "room_3",
      "name": "Room 3",
      "type": "unknown",
      "squareFootage": 221550,
      "isExterior": false,
      "vertices": [
        {
          "x": 60,
          "y": 753.5
        },
        {
          "x": 480,
          "y": 753.5
        },
        {
          "x": 480,
          "y": 1281
        },
        {
          "x": 60,
          "y": 1281
        }
      ],
      "source": "ai-detection",
      "isManual": false,
      "isDeleted": false
    },
    {
      "id": "room_4",
      "name": "Room 4",
      "type": "unknown",
      "squareFootage": 221550,
      "isExterior": false,
      "vertices": [
        {
          "x": 480,
          "y": 753.5
        },
        {
          "x": 900,
          "y": 753.5
        },
        {
          "x": 900,
          "y": 1281
        },
        {
          "x": 480,
          "y": 1281
        }
      ],
      "source": "ai-detection",
      "isManual": false,
      "isDeleted": false
    }
  ],
  "doors": [
    {
      "id": "door_1",
      "position": {
        "x": 140.0625,
        "y": 387.5
      },
      "width": 27.000289350301415,
      "orientation": "vertical",
      "source": "ai-detection",
      "isManual": false,
      "isDeleted": false
    },
    {
      "id": "door_2",
      "position": {
        "x": 459.5625,
        "y": 426.5
      },
      "width": 26.0147193911447,
      "orientation": "vertical",
      "source": "ai-detection",
      "isManual": false,
      "isDeleted": false
    },
    {
      "id": "door_3",
      "position": {
        "x": 740,
        "y": 297
      },
      "width": 30,
      "orientation": "vertical",
      "source": "ai-detection",
      "isManual": false,
      "isDeleted": false
    },
    {
      "id": "door_4",
      "position": {
        "x": 740,
        "y": 367.5
      },
      "width": 31,
      "orientation": "vertical",
      "source": "ai-detection",
      "isManual": false,
      "isDeleted": false
    }
  ],
  "windows": [],
  "measurements": [],
  "metadata": {
    "totalWalls": 37,
    "totalRooms": 4,
    "totalDoors": 4,
    "totalWindows": 0,
    "totalMeasurements": 0,
    "manualEdits": 0,
    "deletions": 0,
    "detectionMethods": [],
    "aiWalls": null,
    "processingTime": 344648470
  }
}